itsicli/__init__.py
itsicli/setup_logging.py
itsicli/content_packs/__init__.py
itsicli/content_packs/content_types.py
itsicli/content_packs/files.py
itsicli/content_packs/model_formats.py
itsicli/content_packs/scaffold.py
itsicli/content_packs/workspace.py
itsicli/content_packs/backup/__init__.py
itsicli/content_packs/backup/convert_backup.py
itsicli/content_packs/backup/extract_models.py
itsicli/content_packs/backup/field_decode.py
itsicli/content_packs/backup/remap_keys.py
itsicli/content_packs/backup/workspace_import.py
itsicli/content_packs/commands/__init__.py
itsicli/content_packs/commands/base.py
itsicli/content_packs/commands/importbackup.py
itsicli/content_packs/commands/init.py
itsicli/content_packs/commands/tidyup.py
itsicli/content_packs/commands/validate.py
itsicli/content_packs/resources/template_README.md
itsicli/content_packs/resources/template_app.conf
itsicli/content_packs/resources/template_manifest.json
itsicli/content_packs/validate/__init__.py
itsicli/content_packs/validate/registry.py
itsicli/content_packs/validate/result.py
itsicli/content_packs/validate/validate_config.py
itsicli/content_packs/validate/validate_icon.py
itsicli/content_packs/validate/validate_metadata.py
itsicli/content_packs/validate/validate_screenshots.py
itsicli-0.0.40.data/scripts/itsi-content-pack
tests/__init__.py
itsicli-0.0.40.dist-info/LICENSE
itsicli-0.0.40.dist-info/METADATA
itsicli-0.0.40.dist-info/WHEEL
itsicli-0.0.40.dist-info/top_level.txt
itsicli-0.0.40.dist-info/RECORD
