Metadata-Version: 2.1
Name: itsicli
Version: 0.0.40
Summary: The ITSI Command Line Interface (CLI)
Home-page: https://github.com/splunk/itsi-cli
Author: Splunk, Inc.
Classifier: Programming Language :: Python :: 3
Classifier: License :: OSI Approved :: Apache Software License
Classifier: Operating System :: OS Independent
Requires-Python: >=3.6
License-File: LICENSE
Requires-Dist: itsimodels (>=0.0.39)
Requires-Dist: python-slugify (>=4.0.0)
